cscdata/__init__.py
cscdata/ckClient.py
cscdata/ckServer.py
cscdata/config.py
cscdata/localAbstract.py
cscdata/localDB.py
cscdata/localInit.py
cscdata/localManager.py
cscdata/map.py
cscdata/utils.py
cscdata/ckdata/__init__.py
cscdata/ckdata/ckClient.py
cscdata/ckdata/ckServer.py
cscdata/ckdata/map.py
cscdata/ckdata/utils.py
cscdata/localdata/__init__.py
cscdata/localdata/config.py
cscdata/localdata/context.py
cscdata/localdata/context_.py
cscdata/localdata/decorators.py
cscdata/localdata/localAbstract.py
cscdata/localdata/localInit.py
cscdata/localdata/stock_utils.py
cscdata/localdata/utils.py
cscdata/localdata/fut_xhn/README.md
cscdata/localdata/fut_xhn/__init__.py
cscdata/localdata/fut_xhn/cfg.py
cscdata/localdata/fut_xhn/context.py
cscdata/localdata/fut_xhn/context_stk.py
cscdata/localdata/fut_xhn/demo.py
cscdata/localdata/fut_xhn/lib.py
cscdata/localdata/fut_xhn/test_rp.py
cscdata/localdata/fut_xhn/utils.py
cscdata/localdata/stock/__init__.py
cscdata/localdata/stock/context_stk.py
cscdata/localdata/stock/lib.py
cscdata/localdata/stock/utils.py
cscdata_v0/__init__.py
cscdata_v0/ckClient.py
cscdata_v0/ckServer.py
cscdata_v0/config.py
cscdata_v0/localAbstract.py
cscdata_v0/localInit.py
cscdata_v0/map.py
cscdata_v0/utils.py
cscdata_v1/__init__.py
cscdata_v1/ckdata/__init__.py
cscdata_v1/ckdata/ckClient.py
cscdata_v1/ckdata/ckServer.py
cscdata_v1/ckdata/map.py
cscdata_v1/ckdata/utils.py
cscdata_v1/localdata/__init__.py
cscdata_v1/localdata/config.py
cscdata_v1/localdata/localAbstract.py
cscdata_v1/localdata/localInit.py
cscdata_v1/localdata/utils.py
cscdata-0.1.7.dist-info/METADATA
cscdata-0.1.7.dist-info/WHEEL
cscdata-0.1.7.dist-info/top_level.txt
cscdata-0.1.7.dist-info/RECORD
