Metadata-Version: 2.1
Name: cscdata
Version: 0.1.7
Summary: stk context support
Author: rp
